CNN.py
Datamodule.py
Evaluation.py
Utils.py
Visualization.py
activations.py
function.py
functional.py
layer.py
linear.py
losses.py
model.py
net.py
optimizer.py
PyVisionTeam17-0.0.5.dist-info/LICENSE.txt
PyVisionTeam17-0.0.5.dist-info/METADATA
PyVisionTeam17-0.0.5.dist-info/WHEEL
PyVisionTeam17-0.0.5.dist-info/top_level.txt
PyVisionTeam17-0.0.5.dist-info/RECORD
