Metadata-Version: 2.1
Name: PyVisionTeam17
Version: 0.0.5
Summary: Deep Learning Framework
Home-page: https://github.com/HendMuhmmad/Deep-Learning-Framework
License: MIT
Platform: UNKNOWN
Requires-Dist: matplotlib (<=3.1.3)
Requires-Dist: pillow (<=8.0.1)
Requires-Dist: numpy (<=1.17.5)
Requires-Dist: pandas (<=0.25.1)
